<?xml version="1.0" encoding="utf-8"?>
<databaseChangeLog
    xmlns="http://www.liquibase.org/xml/ns/dbchangelog"
    xmlns:ext="http://www.liquibase.org/xml/ns/dbchangelog-ext"
    xmlns:xsi="http://www.w3.org/2001/XMLSchema-instance"
    xsi:schemaLocation="
    http://www.liquibase.org/xml/ns/dbchangelog
    https://www.liquibase.org/xml/ns/dbchangelog/dbchangelog-4.33.xsd
    http://www.liquibase.org/xml/ns/dbchangelog-ext
    https://www.liquibase.org/xml/ns/dbchangelog/dbchangelog-ext.xsd">

    <property name="now" value="current_timestamp" dbms="postgresql"/>
    <property name="floatType" value="float4" dbms="postgresql"/>
    <property name="clobType" value="clob" dbms="postgresql"/>
    <property name="blobType" value="blob" dbms="postgresql"/>
    <property name="uuidType" value="uuid" dbms="postgresql"/>
    <property name="datetimeType" value="datetime" dbms="postgresql"/>
    <property name="timeType" value="time(6)" dbms="postgresql"/>

    <include file="config/liquibase/changelog/00000000000000_initial_schema.xml" relativeToChangelogFile="false"/>
    <include file="config/liquibase/changelog/00000000000003_auth_tables.xml" relativeToChangelogFile="false"/>
    <include file="config/liquibase/changelog/00000000000004_properties.xml" relativeToChangelogFile="false"/>
    <!-- Include changelogs shipped inside classpath JARs -->
    <includeAll path="META-INF/sql/org.postgresql.Driver/liquibase"
                relativeToChangelogFile="false"
                errorIfMissingOrEmpty="false"/>
</databaseChangeLog>
